winmemory/__init__.py
winmemory/winmemory.py
winmemory-0.1.0.dist-info/METADATA
winmemory-0.1.0.dist-info/WHEEL
winmemory-0.1.0.dist-info/top_level.txt
winmemory-0.1.0.dist-info/RECORD
