Metadata-Version: 2.1
Name: winmemory
Version: 0.1.0
Summary: Memory manipulation using python and ctypes
Author: ph_thienphu1006
Author-email: phualan1006@gmail.com
Classifier: Programming Language :: Python :: 3
Classifier: License :: OSI Approved :: MIT License
Classifier: Operating System :: Microsoft :: Windows
